orthoxml/__init__.py
orthoxml/__main__.py
orthoxml/cli.py
orthoxml/custom_parsers.py
orthoxml/logger.py
orthoxml/parsers.py
orthoxml/py.typed
orthoxml/streamfilters.py
orthoxml/utils.py
orthoxml/converters/__init__.py
orthoxml/converters/from_nhx.py
orthoxml/converters/from_orthofinder.py
orthoxml/converters/to_nhx.py
orthoxml/legacy/exceptions.py
orthoxml/legacy/exporters.py
orthoxml/legacy/loaders.py
orthoxml/legacy/models.py
orthoxml/legacy/tree.py
orthoxml/schemas/orthoxml-0.3.xsd
orthoxml/schemas/orthoxml-0.4.xsd
orthoxml/schemas/orthoxml-0.5.xsd
orthoxml_tools-1.2.1.dist-info/METADATA
orthoxml_tools-1.2.1.dist-info/WHEEL
orthoxml_tools-1.2.1.dist-info/entry_points.txt
orthoxml_tools-1.2.1.dist-info/licenses/LICENSE
orthoxml_tools-1.2.1.dist-info/RECORD
