Metadata-Version: 2.4
Name: orthoxml-tools
Version: 1.2.1
Summary: Tools for working with OrthoXML files.
Author-email: Ali Yazdizadeh <aliyzd1379@gmail.com>
License-File: LICENSE
Requires-Python: >=3.9
Requires-Dist: dendropy>=5.0.8
Requires-Dist: importlib-resources>=5.1; python_version < '3.10'
Requires-Dist: lxml>=5.3.0
Provides-Extra: test
Requires-Dist: pytest-cov>=3.0.0; extra == 'test'
Requires-Dist: pytest>=7.0.0; extra == 'test'
